piecutter/__init__.py
piecutter/commands/__init__.py
piecutter/commands/add.py
piecutter/generators/code.py
piecutter/generators/files.py
piecutter/generators/folders.py
piecutter/main.py
piecutter/utils.py
piecutter_cli-0.2.4.dist-info/entry_points.txt
piecutter_cli-0.2.4.dist-info/LICENSE
piecutter_cli-0.2.4.dist-info/WHEEL
piecutter_cli-0.2.4.dist-info/METADATA
piecutter_cli-0.2.4.dist-info/RECORD
