Metadata-Version: 2.1
Name: piecutter-cli
Version: 0.2.4
Summary: A CLI tool for building ML projects from research to production in no time.
License: MIT
Author: g0nz4rth
Author-email: arthurgs2007@gmail.com
Requires-Python: >=3.8,<4.0
Classifier: License :: OSI Approved :: MIT License
Classifier: Programming Language :: Python :: 3
Classifier: Programming Language :: Python :: 3.10
Classifier: Programming Language :: Python :: 3.8
Classifier: Programming Language :: Python :: 3.9
Requires-Dist: click (==8.1.3)
Requires-Dist: typer (==0.6.1)
